web3storagepy/__init__.py
web3storagepy-0.0.1.dist-info/LICENSE
web3storagepy-0.0.1.dist-info/METADATA
web3storagepy-0.0.1.dist-info/WHEEL
web3storagepy-0.0.1.dist-info/top_level.txt
web3storagepy-0.0.1.dist-info/RECORD
