Metadata-Version: 2.1
Name: web3storagepy
Version: 0.0.1
Summary: An IPFS web3.storage unofficial library.
Home-page: https://github.com/tahaafarooq/web3.storage
Download-URL: 
Author: Tahaa Farooq
Author-email: tahacodez@gmail.com
License: MIT
Keywords: web3 storage,web3web3 storage apiIPFSweb3 apiIPFS api,python-tanzania
Classifier: Intended Audience :: Developers
Classifier: Topic :: Software Development :: Build Tools
Classifier: License :: OSI Approved :: MIT License
Classifier: Programming Language :: Python :: 3.11
Requires-Python: >=3.7
License-File: LICENSE
Requires-Dist: libmagic
Requires-Dist: python-magic-bin (==0.4.14)
Requires-Dist: requests
